acoupi/__init__.py
acoupi/__main__.py
acoupi/data.py
acoupi/py.typed
acoupi/cli/__init__.py
acoupi/cli/base.py
acoupi/cli/config.py
acoupi/cli/deployment.py
acoupi/cli/tasks.py
acoupi/cli/workers.py
acoupi/components/__init__.py
acoupi/components/audio_recorder.py
acoupi/components/message_factories.py
acoupi/components/messengers.py
acoupi/components/model_template.py
acoupi/components/output_cleaners.py
acoupi/components/processing_filters.py
acoupi/components/recording_conditions.py
acoupi/components/recording_schedulers.py
acoupi/components/saving_filters.py
acoupi/components/saving_managers.py
acoupi/components/summariser.py
acoupi/components/types.py
acoupi/components/message_stores/__init__.py
acoupi/components/message_stores/sqlite/__init__.py
acoupi/components/message_stores/sqlite/database.py
acoupi/components/message_stores/sqlite/message_store.py
acoupi/components/message_stores/sqlite/types.py
acoupi/components/models/__init__.py
acoupi/components/stores/__init__.py
acoupi/components/stores/sqlite/__init__.py
acoupi/components/stores/sqlite/database.py
acoupi/components/stores/sqlite/store.py
acoupi/components/stores/sqlite/types.py
acoupi/devices/__init__.py
acoupi/devices/audio.py
acoupi/devices/rpi.py
acoupi/programs/__init__.py
acoupi/programs/connected.py
acoupi/programs/default.py
acoupi/programs/test.py
acoupi/programs/core/__init__.py
acoupi/programs/core/base.py
acoupi/programs/core/workers.py
acoupi/programs/templates/__init__.py
acoupi/programs/templates/basic.py
acoupi/programs/templates/detection.py
acoupi/programs/templates/messaging.py
acoupi/system/__init__.py
acoupi/system/apps.py
acoupi/system/celery.py
acoupi/system/constants.py
acoupi/system/deployments.py
acoupi/system/exceptions.py
acoupi/system/files.py
acoupi/system/lifecycle.py
acoupi/system/programs.py
acoupi/system/scripts.py
acoupi/system/services.py
acoupi/system/state.py
acoupi/system/tasks.py
acoupi/system/templates.py
acoupi/system/config/__init__.py
acoupi-0.3.2.dist-info/METADATA
acoupi-0.3.2.dist-info/WHEEL
acoupi-0.3.2.dist-info/entry_points.txt
acoupi-0.3.2.dist-info/licenses/LICENSE
acoupi-0.3.2.dist-info/RECORD
