Metadata-Version: 2.4
Name: acoupi
Version: 0.3.2
Summary: Classifier for bioacoustic devices
Author-email: Aude Vuilli <aude.vuilliomenet.18@ucl.ac.uk>, Santiago Martinez Balvanera <santiago.balvanera.20@ucl.uk.ac>
License: GPL-3.0
License-File: LICENSE
Requires-Python: <3.14,>=3.9
Requires-Dist: astral>=3.2
Requires-Dist: celery>=5.4.0
Requires-Dist: click>=8.1.3
Requires-Dist: eventlet>=0.36.1
Requires-Dist: jinja2>=3.1.2
Requires-Dist: omegaconf>=2.3.0
Requires-Dist: paho-mqtt>=1.6.1
Requires-Dist: pony>=0.7.16
Requires-Dist: pyaudio>=0.2.13
Requires-Dist: pydantic-extra-types>=2.9.0
Requires-Dist: pydantic-settings>=2.0.3
Requires-Dist: pydantic>=1.10.8
Requires-Dist: pygments>=2.18.0
Requires-Dist: pytz>=2023.3.post1
Requires-Dist: pyyaml>=6.0
Requires-Dist: requests>=2.31.0
